contrast/Gadget.py
contrast/__init__.py
contrast/utils.py
contrast/detectors/AdLink.py
contrast/detectors/Detector.py
contrast/detectors/Dummies.py
contrast/detectors/LC400Buffer.py
contrast/detectors/Lima.py
contrast/detectors/Merlin.py
contrast/detectors/Ni6602.py
contrast/detectors/Pilatus.py
contrast/detectors/TangoAttributeDetector.py
contrast/detectors/Xspress3.py
contrast/detectors/__init__.py
contrast/environment/__init__.py
contrast/environment/data.py
contrast/environment/scheduling.py
contrast/environment/snapshots.py
contrast/motors/E727.py
contrast/motors/LC400.py
contrast/motors/Motor.py
contrast/motors/PseudoMotor.py
contrast/motors/SmaractMotor.py
contrast/motors/TangoAttributeMotor.py
contrast/motors/TangoMotor.py
contrast/motors/__init__.py
contrast/recorders/Hdf5Recorder.py
contrast/recorders/PlotRecorder.py
contrast/recorders/Recorder.py
contrast/recorders/__init__.py
contrast/scans/AScan.py
contrast/scans/Mesh.py
contrast/scans/NpointFlyscan.py
contrast/scans/Scan.py
contrast/scans/Spiral.py
contrast/scans/Tweak.py
contrast/scans/__init__.py
contrast-0.0.1.dist-info/LICENSE
contrast-0.0.1.dist-info/METADATA
contrast-0.0.1.dist-info/WHEEL
contrast-0.0.1.dist-info/top_level.txt
contrast-0.0.1.dist-info/RECORD
