Metadata-Version: 2.1
Name: contrast
Version: 0.0.1
Summary: Light weight data acquisition framework for orchestrating beamline experiments.
Home-page: https://github.com/alexbjorling/contrast
Author: Alexander Björling
Author-email: alexander.bjorling@maxiv.lu.se
License: UNKNOWN
Platform: UNKNOWN
Classifier: Programming Language :: Python :: 3
Classifier: License :: OSI Approved :: MIT License
Classifier: Operating System :: OS Independent
Requires-Python: >=3.6
